tocode/__init__.py
tocode/__inner_files__/__init__.py
tocode/__inner_files__/_built_in/__init__.py
tocode/__inner_files__/_built_in/_built_in_file_manager.py
tocode/__inner_files__/_gen/__code_gen_list__.py
tocode/__inner_files__/_gen/__init__.py
tocode/__inner_files__/_src/__code_sr_list__.py
tocode/__inner_files__/_src/__init__.py
tocode/_literal_eval_par/__init__.py
tocode/_literal_eval_par/_literal_eval.py
tocode/_literal_eval_par/_str_parser.py
tocode-0.1.3.dist-info/LICENSE
tocode-0.1.3.dist-info/METADATA
tocode-0.1.3.dist-info/WHEEL
tocode-0.1.3.dist-info/top_level.txt
tocode-0.1.3.dist-info/RECORD
