Metadata-Version: 2.1
Name: tocode
Version: 0.1.3
Summary: a python library that convert string to code.
Home-page: https://github.com/Amir-Shamsi/tocode
Author: Amir Shamsi
Author-email: amirshamsi.github@gmail.com
License: MIT
Download-URL: https://github.com/Amir-Shamsi/tocode/archive/refs/tags/0.1.1.tar.gz
Keywords: tocode,convertor,string-to-code,code,string,code-generator,generator
Platform: UNKNOWN
Classifier: Development Status :: 3 - Alpha
Classifier: Intended Audience :: Developers
Classifier: Topic :: Software Development :: Build Tools
Classifier: License :: OSI Approved :: MIT License
Classifier: Programming Language :: Python :: 3.4
Classifier: Programming Language :: Python :: 3.5
Classifier: Programming Language :: Python :: 3.6
Classifier: Programming Language :: Python :: 3.7
Classifier: Programming Language :: Python :: 3.8
Classifier: Programming Language :: Python :: 3.9
Classifier: Programming Language :: Python :: 3.10
License-File: LICENSE
